{
  "inventory_data": [
    {
      "itemCount": 1,
      "item": "STARTER_SWORD"
    },
    {
      "itemCount": 5,
      "item": "COIN"
    },
    {
      "itemCount": 63,
      "item": "HEAL_POTION"
    }
  ],
  "hotbar_data": [
    {
      "itemCount": 0,
      "item": null
    },
    {
      "itemCount": 0,
      "item": null
    },
    {
      "itemCount": 0,
      "item": null
    },
    {
      "itemCount": 0,
      "item": null
    },
    {
      "itemCount": 0,
      "item": null
    },
    {
      "itemCount": 0,
      "item": null
    },
    {
      "itemCount": 0,
      "item": null
    },
    {
      "itemCount": 0,
      "item": null
    },
    {
      "itemCount": 0,
      "item": null
    },
    {
      "itemCount": 0,
      "item": null
    }
  ]
}